easymed/__init__.py
easymed/CV/__init__.py
easymed/CV/metrics.py
easymed/CV/utils.py
easymed/CV/model/__init__.py
easymed/CV/model/fcn.py
easymed/CV/model/unet.py
easymed/CV/modules/__init__.py
easymed/CV/modules/blocks.py
easymed/CV/modules/down.py
easymed/CV/modules/up.py
easymed-0.0.6.dist-info/LICENSE
easymed-0.0.6.dist-info/METADATA
easymed-0.0.6.dist-info/WHEEL
easymed-0.0.6.dist-info/top_level.txt
easymed-0.0.6.dist-info/RECORD
