Metadata-Version: 2.1
Name: easymed
Version: 0.0.6
Summary: One stop medical toolkit
Home-page: https://github.com/EasyMed2023
Author: EasyMed in BUPT
Author-email: bool1020@bupt.edu.cn
License: MIT License
Platform: all
Classifier: Programming Language :: Python
Classifier: Programming Language :: Python :: 3.7
Classifier: Programming Language :: Python :: 3.10
Requires-Python: >=3.7
License-File: LICENSE
Requires-Dist: tqdm
Requires-Dist: torch
Requires-Dist: opencv-python
